README.md
setup.py
probecard/__init__.py
probecard/__main__.py
probecard/probecard.py
probecard.egg-info/PKG-INFO
probecard.egg-info/SOURCES.txt
probecard.egg-info/dependency_links.txt
probecard.egg-info/requires.txt
probecard.egg-info/top_level.txt
probecard/bin/probecard
probecard/daq/AllPixelsDaq.py
probecard/daq/BaseProbecardThread.py
probecard/daq/BasicDaqWindow.py
probecard/daq/ExampleDaq.py
probecard/daq/FinalizeDataThread.py
probecard/daq/MultiPixelDaq.py
probecard/daq/SinglePixelDaq.py
probecard/daq/__init__.py
probecard/daq/test.py
probecard/daq/utilities/Excel.py
probecard/daq/utilities/__init__.py
probecard/daq/utilities/controller.py
probecard/daq/utilities/controller_maps.py
probecard/daq/utilities/emailbot.py
probecard/daq/utilities/magnitudes.py
probecard/daq/utilities/max.py
probecard/daq/windows/DetailWindow.py
probecard/daq/windows/IV_Window.py
probecard/daq/windows/__init__.py
probecard/menu/MenuWidget.py
probecard/menu/RegionWindow.py
probecard/menu/Saveable.py
probecard/menu/StateWindow.py
probecard/menu/TwoPaneWindow.py
probecard/menu/ValueHandler.py
probecard/menu/__init__.py