Metadata-Version: 2.1
Name: probecard
Version: 0.2.2
Summary: GUI for probecard measurements.
Home-page: https://github.com/Tsangares/Probecard/tree/probecardv1.4
Author: William Wyatt
Author-email: wwyatt@ucsc.edu
License: UNKNOWN
Platform: UNKNOWN
Classifier: Programming Language :: Python :: 3
Classifier: License :: OSI Approved :: MIT License
